test/__init__.py
test/test_error.py
test/test_page_of_tools.py
test/test_page_of_tools_all_of.py
test/test_response_page_metadata.py
test/test_response_page_metadata_links.py
test/test_tool.py
test/test_tool_api.py
toolregistryclient/__init__.py
toolregistryclient/api_client.py
toolregistryclient/configuration.py
toolregistryclient/exceptions.py
toolregistryclient/rest.py
toolregistryclient/api/__init__.py
toolregistryclient/api/tool_api.py
toolregistryclient/models/__init__.py
toolregistryclient/models/error.py
toolregistryclient/models/page_of_tools.py
toolregistryclient/models/page_of_tools_all_of.py
toolregistryclient/models/response_page_metadata.py
toolregistryclient/models/response_page_metadata_links.py
toolregistryclient/models/tool.py
tool_registry_client-0.1.0.dist-info/LICENSE
tool_registry_client-0.1.0.dist-info/METADATA
tool_registry_client-0.1.0.dist-info/WHEEL
tool_registry_client-0.1.0.dist-info/top_level.txt
tool_registry_client-0.1.0.dist-info/RECORD
