Metadata-Version: 2.1
Name: tool-registry-client
Version: 0.1.0
Summary: Tool Registry Library for Python
Home-page: https://github.com/Sage-Bionetworks/tool-registry-client
Author: The Tool Registry Team
Author-email: thomas.schaffter@sagebionetworks.org
License: Apache
Project-URL: Source Code, https://github.com/Sage-Bionetworks/tool-registry-client
Project-URL: Bug Tracker, https://github.com/Sage-Bionetworks/tool-registry-client/issues
Platform: UNKNOWN
Classifier: Development Status :: 2 - Pre-Alpha
Classifier: Programming Language :: Python
Classifier: Programming Language :: Python :: 3.6
Classifier: Programming Language :: Python :: 3.7
Classifier: Programming Language :: Python :: 3.8
Classifier: Operating System :: OS Independent
Classifier: Intended Audience :: Developers
Classifier: Intended Audience :: Science/Research
Classifier: License :: OSI Approved :: Apache Software License
Classifier: Topic :: Software Development :: Libraries
Classifier: Topic :: Scientific/Engineering
Classifier: Topic :: Scientific/Engineering :: Bio-Informatics
Requires-Python: >=3.6.*
Requires-Dist: click (>=7.1.2)
Requires-Dist: jsonschema (>=3.2.0)
Requires-Dist: synapseclient (>=2.2.0)
